faker_pk/__init__.py
faker_pk/address.py
faker_pk/company.py
faker_pk/personal.py
faker_pk/provider.py
faker_pk/utils.py
faker_pk-0.1.9.dist-info/METADATA
faker_pk-0.1.9.dist-info/WHEEL
faker_pk-0.1.9.dist-info/top_level.txt
faker_pk-0.1.9.dist-info/RECORD
