Metadata-Version: 2.4
Name: faker-pk
Version: 0.1.9
Summary: Fake data generator for Pakistani names, CNICs, personal info, address info, job titles, IBAN, Bank names, cities, provinces, castes, sect, network providers, job aware salaries and companies info.
Author: Muhammad Khubaib Ahmad
Author-email: Muhammad Khubaib Ahmad <khubaib0.1ai@gmail.com>
License: MIT
Project-URL: Homepage, https://github.com/Khubaib8281/faker-pk
Keywords: faker,pakistan,data,mock,testing
Classifier: Programming Language :: Python :: 3
Classifier: License :: OSI Approved :: MIT License
Classifier: Operating System :: OS Independent
Requires-Python: >=3.8
